inception_fid_weights_zst/__init__.py
inception_fid_weights_zst/install_inception.py
inception_fid_weights_zst-0.1.0.dist-info/METADATA
inception_fid_weights_zst-0.1.0.dist-info/WHEEL
inception_fid_weights_zst-0.1.0.dist-info/entry_points.txt
inception_fid_weights_zst-0.1.0.dist-info/top_level.txt
inception_fid_weights_zst-0.1.0.dist-info/RECORD
