Metadata-Version: 2.4
Name: inception-fid-weights-zst
Version: 0.1.0
Summary: Loader that assembles Zstandard-sharded Inception-V3 weight for Clean-FID
Author: Your Name
Requires-Python: >=3.8
Requires-Dist: inception-fid-weights-zst-shard01==0.1.0
Requires-Dist: inception-fid-weights-zst-shard02==0.1.0
Requires-Dist: zstandard>=0.22.0
